{"nodes": [{"id": "next_intl_server", "label": "next-intl-server.ts", "file_type": "code", "source_file": "src/compat/next-intl-server.ts", "source_location": "L1"}, {"id": "next_intl_server_setrequestlocale", "label": "setRequestLocale()", "file_type": "code", "source_file": "src/compat/next-intl-server.ts", "source_location": "L8"}, {"id": "next_intl_server_gettranslations", "label": "getTranslations()", "file_type": "code", "source_file": "src/compat/next-intl-server.ts", "source_location": "L12"}, {"id": "next_intl_server_getlocale", "label": "getLocale()", "file_type": "code", "source_file": "src/compat/next-intl-server.ts", "source_location": "L19"}, {"id": "next_intl_server_getmessages", "label": "getMessages()", "file_type": "code", "source_file": "src/compat/next-intl-server.ts", "source_location": "L23"}], "edges": [{"source": "next_intl_server", "target": "next_intl_server_setrequestlocale", "relation": "contains", "confidence": "EXTRACTED", "source_file": "src/compat/next-intl-server.ts", "source_location": "L8", "weight": 1.0}, {"source": "next_intl_server", "target": "next_intl_server_gettranslations", "relation": "contains", "confidence": "EXTRACTED", "source_file": "src/compat/next-intl-server.ts", "source_location": "L12", "weight": 1.0}, {"source": "next_intl_server", "target": "next_intl_server_getlocale", "relation": "contains", "confidence": "EXTRACTED", "source_file": "src/compat/next-intl-server.ts", "source_location": "L19", "weight": 1.0}, {"source": "next_intl_server", "target": "next_intl_server_getmessages", "relation": "contains", "confidence": "EXTRACTED", "source_file": "src/compat/next-intl-server.ts", "source_location": "L23", "weight": 1.0}]}