{"nodes": [{"id": "ai_translate", "label": "ai-translate.ts", "file_type": "code", "source_file": "lib/ai-translate.ts", "source_location": "L1"}, {"id": "ai_translate_autotranslate", "label": "autoTranslate()", "file_type": "code", "source_file": "lib/ai-translate.ts", "source_location": "L11"}], "edges": [{"source": "ai_translate", "target": "settings", "relation": "imports_from", "confidence": "EXTRACTED", "source_file": "lib/ai-translate.ts", "source_location": "L1", "weight": 1.0}, {"source": "ai_translate", "target": "settings", "relation": "imports_from", "confidence": "EXTRACTED", "source_file": "lib/ai-translate.ts", "source_location": "L2", "weight": 1.0}, {"source": "ai_translate", "target": "llmprovider", "relation": "imports_from", "confidence": "EXTRACTED", "source_file": "lib/ai-translate.ts", "source_location": "L3", "weight": 1.0}, {"source": "ai_translate", "target": "i18n_db", "relation": "imports_from", "confidence": "EXTRACTED", "source_file": "lib/ai-translate.ts", "source_location": "L4", "weight": 1.0}, {"source": "ai_translate", "target": "ai_translate_autotranslate", "relation": "contains", "confidence": "EXTRACTED", "source_file": "lib/ai-translate.ts", "source_location": "L11", "weight": 1.0}]}