{"nodes": [{"id": "sql", "label": "sql.ts", "file_type": "code", "source_file": "lib/sql.ts", "source_location": "L1"}, {"id": "sql_snaketocamel", "label": "snakeToCamel()", "file_type": "code", "source_file": "lib/sql.ts", "source_location": "L10"}, {"id": "sql_cameltosnake", "label": "camelToSnake()", "file_type": "code", "source_file": "lib/sql.ts", "source_location": "L15"}, {"id": "sql_maprow", "label": "mapRow()", "file_type": "code", "source_file": "lib/sql.ts", "source_location": "L32"}, {"id": "sql_isjsonstring", "label": "isJsonString()", "file_type": "code", "source_file": "lib/sql.ts", "source_location": "L62"}, {"id": "sql_sql", "label": "sql()", "file_type": "code", "source_file": "lib/sql.ts", "source_location": "L86"}, {"id": "sql_querymany", "label": "queryMany()", "file_type": "code", "source_file": "lib/sql.ts", "source_location": "L108"}, {"id": "sql_queryone", "label": "queryOne()", "file_type": "code", "source_file": "lib/sql.ts", "source_location": "L117"}, {"id": "sql_execute", "label": "execute()", "file_type": "code", "source_file": "lib/sql.ts", "source_location": "L127"}, {"id": "sql_withtransaction", "label": "withTransaction()", "file_type": "code", "source_file": "lib/sql.ts", "source_location": "L143"}, {"id": "sql_assertsafeidentifier", "label": "assertSafeIdentifier()", "file_type": "code", "source_file": "lib/sql.ts", "source_location": "L168"}, {"id": "sql_buildinsert", "label": "buildInsert()", "file_type": "code", "source_file": "lib/sql.ts", "source_location": "L187"}, {"id": "sql_buildupdate", "label": "buildUpdate()", "file_type": "code", "source_file": "lib/sql.ts", "source_location": "L231"}, {"id": "sql_mapcategoryfromrow", "label": "mapCategoryFromRow()", "file_type": "code", "source_file": "lib/sql.ts", "source_location": "L281"}, {"id": "sql_mapprojectfromrow", "label": "mapProjectFromRow()", "file_type": "code", "source_file": "lib/sql.ts", "source_location": "L295"}, {"id": "sql_mapclientfromrow", "label": "mapClientFromRow()", "file_type": "code", "source_file": "lib/sql.ts", "source_location": "L309"}, {"id": "sql_mapproductfromrow", "label": "mapProductFromRow()", "file_type": "code", "source_file": "lib/sql.ts", "source_location": "L326"}, {"id": "sql_serializevalue", "label": "serializeValue()", "file_type": "code", "source_file": "lib/sql.ts", "source_location": "L346"}], "edges": [{"source": "sql", "target": "pg", "relation": "imports_from", "confidence": "EXTRACTED", "source_file": "lib/sql.ts", "source_location": "L1", "weight": 1.0}, {"source": "sql", "target": "pg", "relation": "imports_from", "confidence": "EXTRACTED", "source_file": "lib/sql.ts", "source_location": "L2", "weight": 1.0}, {"source": "sql", "target": "crypto", "relation": "imports_from", "confidence": "EXTRACTED", "source_file": "lib/sql.ts", "source_location": "L3", "weight": 1.0}, {"source": "sql", "target": "sql_snaketocamel", "relation": "contains", "confidence": "EXTRACTED", "source_file": "lib/sql.ts", "source_location": "L10", "weight": 1.0}, {"source": "sql", "target": "sql_cameltosnake", "relation": "contains", "confidence": "EXTRACTED", "source_file": "lib/sql.ts", "source_location": "L15", "weight": 1.0}, {"source": "sql", "target": "sql_maprow", "relation": "contains", "confidence": "EXTRACTED", "source_file": "lib/sql.ts", "source_location": "L32", "weight": 1.0}, {"source": "sql", "target": "sql_isjsonstring", "relation": "contains", "confidence": "EXTRACTED", "source_file": "lib/sql.ts", "source_location": "L62", "weight": 1.0}, {"source": "sql", "target": "sql_sql", "relation": "contains", "confidence": "EXTRACTED", "source_file": "lib/sql.ts", "source_location": "L86", "weight": 1.0}, {"source": "sql", "target": "sql_querymany", "relation": "contains", "confidence": "EXTRACTED", "source_file": "lib/sql.ts", "source_location": "L108", "weight": 1.0}, {"source": "sql", "target": "sql_queryone", "relation": "contains", "confidence": "EXTRACTED", "source_file": "lib/sql.ts", "source_location": "L117", "weight": 1.0}, {"source": "sql", "target": "sql_execute", "relation": "contains", "confidence": "EXTRACTED", "source_file": "lib/sql.ts", "source_location": "L127", "weight": 1.0}, {"source": "sql", "target": "sql_withtransaction", "relation": "contains", "confidence": "EXTRACTED", "source_file": "lib/sql.ts", "source_location": "L143", "weight": 1.0}, {"source": "sql", "target": "sql_assertsafeidentifier", "relation": "contains", "confidence": "EXTRACTED", "source_file": "lib/sql.ts", "source_location": "L168", "weight": 1.0}, {"source": "sql", "target": "sql_buildinsert", "relation": "contains", "confidence": "EXTRACTED", "source_file": "lib/sql.ts", "source_location": "L187", "weight": 1.0}, {"source": "sql", "target": "sql_buildupdate", "relation": "contains", "confidence": "EXTRACTED", "source_file": "lib/sql.ts", "source_location": "L231", "weight": 1.0}, {"source": "sql", "target": "db_types", "relation": "imports_from", "confidence": "EXTRACTED", "source_file": "lib/sql.ts", "source_location": "L278", "weight": 1.0}, {"source": "sql", "target": "sql_mapcategoryfromrow", "relation": "contains", "confidence": "EXTRACTED", "source_file": "lib/sql.ts", "source_location": "L281", "weight": 1.0}, {"source": "sql", "target": "sql_mapprojectfromrow", "relation": "contains", "confidence": "EXTRACTED", "source_file": "lib/sql.ts", "source_location": "L295", "weight": 1.0}, {"source": "sql", "target": "sql_mapclientfromrow", "relation": "contains", "confidence": "EXTRACTED", "source_file": "lib/sql.ts", "source_location": "L309", "weight": 1.0}, {"source": "sql", "target": "sql_mapproductfromrow", "relation": "contains", "confidence": "EXTRACTED", "source_file": "lib/sql.ts", "source_location": "L326", "weight": 1.0}, {"source": "sql", "target": "sql_serializevalue", "relation": "contains", "confidence": "EXTRACTED", "source_file": "lib/sql.ts", "source_location": "L346", "weight": 1.0}, {"source": "sql_maprow", "target": "sql_snaketocamel", "relation": "calls", "confidence": "INFERRED", "source_file": "lib/sql.ts", "source_location": "L36", "weight": 0.8}, {"source": "sql_maprow", "target": "sql_isjsonstring", "relation": "calls", "confidence": "INFERRED", "source_file": "lib/sql.ts", "source_location": "L48", "weight": 0.8}, {"source": "sql_queryone", "target": "sql_maprow", "relation": "calls", "confidence": "INFERRED", "source_file": "lib/sql.ts", "source_location": "L121", "weight": 0.8}, {"source": "sql_buildinsert", "target": "sql_assertsafeidentifier", "relation": "calls", "confidence": "INFERRED", "source_file": "lib/sql.ts", "source_location": "L191", "weight": 0.8}, {"source": "sql_buildinsert", "target": "sql_cameltosnake", "relation": "calls", "confidence": "INFERRED", "source_file": "lib/sql.ts", "source_location": "L205", "weight": 0.8}, {"source": "sql_buildinsert", "target": "sql_serializevalue", "relation": "calls", "confidence": "INFERRED", "source_file": "lib/sql.ts", "source_location": "L208", "weight": 0.8}, {"source": "sql_buildupdate", "target": "sql_assertsafeidentifier", "relation": "calls", "confidence": "INFERRED", "source_file": "lib/sql.ts", "source_location": "L237", "weight": 0.8}, {"source": "sql_buildupdate", "target": "sql_cameltosnake", "relation": "calls", "confidence": "INFERRED", "source_file": "lib/sql.ts", "source_location": "L245", "weight": 0.8}, {"source": "sql_buildupdate", "target": "sql_serializevalue", "relation": "calls", "confidence": "INFERRED", "source_file": "lib/sql.ts", "source_location": "L247", "weight": 0.8}]}