{"nodes": [{"id": "select_type", "label": "select-type.tsx", "file_type": "code", "source_file": "components/forms/select-type.tsx", "source_location": "L1"}, {"id": "select_type_formselecttype", "label": "FormSelectType()", "file_type": "code", "source_file": "components/forms/select-type.tsx", "source_location": "L4"}], "edges": [{"source": "select_type", "target": "react_select", "relation": "imports_from", "confidence": "EXTRACTED", "source_file": "components/forms/select-type.tsx", "source_location": "L1", "weight": 1.0}, {"source": "select_type", "target": "simple", "relation": "imports_from", "confidence": "EXTRACTED", "source_file": "components/forms/select-type.tsx", "source_location": "L2", "weight": 1.0}, {"source": "select_type", "target": "select_type_formselecttype", "relation": "contains", "confidence": "EXTRACTED", "source_file": "components/forms/select-type.tsx", "source_location": "L4", "weight": 1.0}]}