{"nodes": [{"id": "stats", "label": "stats.ts", "file_type": "code", "source_file": "lib/stats.ts", "source_location": "L1"}, {"id": "stats_calctotalpercurrency", "label": "calcTotalPerCurrency()", "file_type": "code", "source_file": "lib/stats.ts", "source_location": "L3"}, {"id": "stats_calcnettotalpercurrency", "label": "calcNetTotalPerCurrency()", "file_type": "code", "source_file": "lib/stats.ts", "source_location": "L19"}, {"id": "stats_istransactionincomplete", "label": "isTransactionIncomplete()", "file_type": "code", "source_file": "lib/stats.ts", "source_location": "L45"}, {"id": "stats_incompletetransactionfields", "label": "incompleteTransactionFields()", "file_type": "code", "source_file": "lib/stats.ts", "source_location": "L51"}], "edges": [{"source": "stats", "target": "db_types", "relation": "imports_from", "confidence": "EXTRACTED", "source_file": "lib/stats.ts", "source_location": "L1", "weight": 1.0}, {"source": "stats", "target": "stats_calctotalpercurrency", "relation": "contains", "confidence": "EXTRACTED", "source_file": "lib/stats.ts", "source_location": "L3", "weight": 1.0}, {"source": "stats", "target": "stats_calcnettotalpercurrency", "relation": "contains", "confidence": "EXTRACTED", "source_file": "lib/stats.ts", "source_location": "L19", "weight": 1.0}, {"source": "stats", "target": "stats_istransactionincomplete", "relation": "contains", "confidence": "EXTRACTED", "source_file": "lib/stats.ts", "source_location": "L45", "weight": 1.0}, {"source": "stats", "target": "stats_incompletetransactionfields", "relation": "contains", "confidence": "EXTRACTED", "source_file": "lib/stats.ts", "source_location": "L51", "weight": 1.0}, {"source": "stats_istransactionincomplete", "target": "stats_incompletetransactionfields", "relation": "calls", "confidence": "INFERRED", "source_file": "lib/stats.ts", "source_location": "L46", "weight": 0.8}]}